guolei_py3_qywx/__init__.py
guolei_py3_qywx/server.py
guolei_py3_qywx/webhook.py
guolei_py3_qywx/library/__init__.py
guolei_py3_qywx/library/server.py
guolei_py3_qywx/library/webhook.py
guolei_py3_qywx-2.1.1.dist-info/LICENSE
guolei_py3_qywx-2.1.1.dist-info/METADATA
guolei_py3_qywx-2.1.1.dist-info/WHEEL
guolei_py3_qywx-2.1.1.dist-info/top_level.txt
guolei_py3_qywx-2.1.1.dist-info/RECORD
